hTrackerIU/__init__.py
hTrackerIU/init_db.py
hTrackerIU/main.py
hTrackerIU/api/__init__.py
hTrackerIU/api/dependencies.py
hTrackerIU/api/main.py
hTrackerIU/api/routes.py
hTrackerIU/api/schemas.py
hTrackerIU/application/__init__.py
hTrackerIU/application/service/__init__.py
hTrackerIU/application/service/analytics_service.py
hTrackerIU/application/service/habit_service.py
hTrackerIU/domain/__init__.py
hTrackerIU/domain/model/__init__.py
hTrackerIU/domain/model/completion_log.py
hTrackerIU/domain/model/habit.py
hTrackerIU/domain/model/periodicity.py
hTrackerIU/domain/service/__init__.py
hTrackerIU/domain/service/streak_calculation_service.py
hTrackerIU/infrastructure/__init__.py
hTrackerIU/infrastructure/config.py
hTrackerIU/infrastructure/orm/__init__.py
hTrackerIU/infrastructure/orm/models.py
hTrackerIU/infrastructure/orm/session.py
hTrackerIU/infrastructure/repository/__init__.py
hTrackerIU/infrastructure/repository/habit_repository.py
hTrackerIU/static/asset-manifest.json
hTrackerIU/static/favicon.ico
hTrackerIU/static/index.html
hTrackerIU/static/logo192.png
hTrackerIU/static/logo512.png
hTrackerIU/static/manifest.json
hTrackerIU/static/robots.txt
hTrackerIU/static/static/js/main.826b45d2.js
hTrackerIU/static/static/js/main.826b45d2.js.LICENSE.txt
hTrackerIU/static/static/js/main.826b45d2.js.map
hTrackerIU-0.17.dist-info/METADATA
hTrackerIU-0.17.dist-info/WHEEL
hTrackerIU-0.17.dist-info/entry_points.txt
hTrackerIU-0.17.dist-info/top_level.txt
hTrackerIU-0.17.dist-info/RECORD
